nightly_scripts/__init__.py
nightly_scripts/admin.py
nightly_scripts/apps.py
nightly_scripts/models.py
nightly_scripts/tests.py
nightly_scripts/views.py
nightly_scripts/management/__init__.py
nightly_scripts/management/commands/__init__.py
nightly_scripts/management/commands/execute_nightly_scripts.py
nightly_scripts/migrations/__init__.py
nightly_scripts-0.1.3.dist-info/licenses/LICENSE
nightly_scripts-0.1.3.dist-info/METADATA
nightly_scripts-0.1.3.dist-info/WHEEL
nightly_scripts-0.1.3.dist-info/top_level.txt
nightly_scripts-0.1.3.dist-info/RECORD
