Metadata-Version: 2.4
Name: nightly-scripts
Version: 0.1.3
Summary: Ночные скрипты
Author-email: BARS Group <bars@bars.group>
Project-URL: Homepage, https://stash.bars-open.ru/projects/M3/repos/nightly-scripts/browse
Project-URL: Repository, https://stash.bars-open.ru/scm/m3/nightly-scripts.git
Classifier: Development Status :: 3 - Alpha
Classifier: Programming Language :: Python
Classifier: Programming Language :: Python :: 3
Classifier: Programming Language :: Python :: 3.9
Classifier: Programming Language :: Python :: 3.10
Classifier: Programming Language :: Python :: 3.11
Classifier: Programming Language :: Python :: 3.12
Classifier: Intended Audience :: Developers
Classifier: Environment :: Console
Classifier: Framework :: Django :: 2.2
Classifier: Framework :: Django :: 3.0
Classifier: Framework :: Django :: 3.1
Classifier: Framework :: Django :: 3.2
Classifier: Framework :: Django :: 4.0
Classifier: Framework :: Django :: 4.1
Classifier: Framework :: Django :: 4.2
Classifier: Framework :: Django :: 5.0
Classifier: Framework :: Django :: 5.1
Requires-Python: >=3.9
License-File: LICENSE
Requires-Dist: Django<5.2,>=2.2
Provides-Extra: dev
Requires-Dist: isort<6,>=5.10.1; extra == "dev"
Requires-Dist: flake8<7,>=4.0.1; extra == "dev"
Requires-Dist: pytest<8,>=3.2.5; extra == "dev"
Requires-Dist: pytest-cov<5; extra == "dev"
Requires-Dist: python-semantic-release<9; extra == "dev"
Dynamic: license-file
